MANIFEST.in
README.md
setup.py
django_gearman/__init__.py
django_gearman/decorators.py
django_gearman/models.py
django_gearman.egg-info/PKG-INFO
django_gearman.egg-info/SOURCES.txt
django_gearman.egg-info/dependency_links.txt
django_gearman.egg-info/not-zip-safe
django_gearman.egg-info/requires.txt
django_gearman.egg-info/top_level.txt
django_gearman/management/__init__.py
django_gearman/management/commands/__init__.py
django_gearman/management/commands/gearman_list_tasks.py
django_gearman/management/commands/gearman_worker.py
gearman_example/__init__.py
gearman_example/gearman_jobs.py
gearman_example/management/__init__.py
gearman_example/management/commands/__init__.py
gearman_example/management/commands/gearman_example_client.py