Metadata-Version: 1.1
Name: django-gearman
Version: 0.2
Summary: A convenience wrapper for Gearman clients and workers in Django/Python
Home-page: http://github.com/fwenzel/django-gearman
Author: Frederic Wenzel
Author-email: fwenzel@mozilla.com
License: MPL
Platform: UNKNOWN
Classifier: Development Status :: 4 - Beta
Classifier: Environment :: Web Environment
Classifier: Framework :: Django
Classifier: Intended Audience :: Developers
Classifier: Operating System :: OS Independent
Classifier: Programming Language :: Python
Classifier: Topic :: Software Development :: Libraries :: Python Modules
